slowrevpy/__init__.py
slowrevpy/__main__.py
slowrevpy/__version__.py
slowrevpy/slowrevpy.py
slowrevpy-1.5.1.dist-info/licenses/LICENSE
slowrevpy-1.5.1.dist-info/METADATA
slowrevpy-1.5.1.dist-info/WHEEL
slowrevpy-1.5.1.dist-info/entry_points.txt
slowrevpy-1.5.1.dist-info/top_level.txt
slowrevpy-1.5.1.dist-info/RECORD
