Metadata-Version: 2.4
Name: slowrevpy
Version: 1.5.1
Summary: A basic python script to make slowed + reverbs.
Author-email: Artemii Popovkin <angap4@gmail.com>
License-Expression: MIT
Project-URL: Homepage, https://github.com/Jrol123/slowedreverb_main
Project-URL: Issues, https://github.com/Jrol123/slowedreverb_main/issues
Keywords: python,music,slowed reverb,Jrol123
Classifier: Programming Language :: Python :: 3
Classifier: Operating System :: Unix
Classifier: Operating System :: MacOS :: MacOS X
Classifier: Operating System :: Microsoft :: Windows
Classifier: Topic :: Utilities
Requires-Python: >=3.9
License-File: LICENSE
Requires-Dist: pedalboard
Requires-Dist: soundfile
Requires-Dist: argparse
Requires-Dist: python-ffmpeg
Dynamic: license-file
